torchservant/__init__.py
torchservant/_basic.py
torchservant/config.py
torchservant/data_template.py
torchservant/dataset.py
torchservant/board/__init__.py
torchservant/board/tensorboardx.py
torchservant/board/visdomtools.py
torchservant/cfgenator/__init__.py
torchservant/cfgenator/config.py
torchservant/classicmodels/__init__.py
torchservant/classicmodels/alexnet.py
torchservant/classicmodels/inception.py
torchservant/classicmodels/resnet.py
torchservant/classicmodels/vgg.py
torchservant/modelkeeper/__init__.py
torchservant/modelkeeper/save_load.py
torchservant/modelservant/__init__.py
torchservant/modelservant/ckptmanager.py
torchservant/modelservant/getcudamodel.py
torchservant/modelservant/initialization.py
torchservant/observer/__init__.py
torchservant/procmonitor/__init__.py
torchservant/procmonitor/monitor.py
torchservant/procmonitor/tensorboardx_api.py
torchservant/procmonitor/visdom_api.py
torchservant/stats/__init__.py
torchservant/visualfeature/__init__.py
torchservant/weightransfer/__init__.py
torchservant/weightransfer/weightstransfer.py
torchservant-0.2.2.dist-info/LICENSE
torchservant-0.2.2.dist-info/METADATA
torchservant-0.2.2.dist-info/WHEEL
torchservant-0.2.2.dist-info/top_level.txt
torchservant-0.2.2.dist-info/RECORD
