Metadata-Version: 2.1
Name: torchservant
Version: 0.2.2
Summary: Many useful tools for PyTorch.
Home-page: https://github.com/QixuanAI/torchservant
Author: qxsoftware
Author-email: qxsoftware@163.com
License: GNU GENERAL PUBLIC LICENSE v3
Keywords: servant,visualize,pytorch,tool,util,deeplearning
Platform: UNKNOWN
Classifier: Programming Language :: Python :: 3
Classifier: License :: OSI Approved :: GNU General Public License v3 (GPLv3)
Classifier: Operating System :: OS Independent
Requires-Python: >=3.0
Requires-Dist: torch
